CHANGES.rst
CONTRIBUTORS.rst
DEVELOP.rst
LICENSE.GPL
LICENSE.rst
MANIFEST.in
README.rst
requirements.txt
setup.cfg
setup.py
tox.ini
docs/index.rst
src/collective/__init__.py
src/collective.fieldedit.egg-info/PKG-INFO
src/collective.fieldedit.egg-info/SOURCES.txt
src/collective.fieldedit.egg-info/dependency_links.txt
src/collective.fieldedit.egg-info/entry_points.txt
src/collective.fieldedit.egg-info/namespace_packages.txt
src/collective.fieldedit.egg-info/not-zip-safe
src/collective.fieldedit.egg-info/requires.txt
src/collective.fieldedit.egg-info/top_level.txt
src/collective/fieldedit/__init__.py
src/collective/fieldedit/configure.zcml
src/collective/fieldedit/field_edit_form.pt
src/collective/fieldedit/field_edit_form.py
src/collective/fieldedit/field_edit_form_bs5.pt
src/collective/fieldedit/interfaces.py
src/collective/fieldedit/setuphandlers.py
src/collective/fieldedit/testing.py
src/collective/fieldedit/profiles/default/browserlayer.xml
src/collective/fieldedit/profiles/default/metadata.xml
src/collective/fieldedit/profiles/uninstall/browserlayer.xml
src/collective/fieldedit/tests/__init__.py
src/collective/fieldedit/tests/test_field_edit_form.py
src/collective/fieldedit/tests/test_robot.py
src/collective/fieldedit/tests/test_setup.py
src/collective/fieldedit/tests/robot/test_example.robot