Metadata-Version: 2.1
Name: collective.fieldedit
Version: 1.0
Summary: A flexible form to edit selected fields of a content type.
Home-page: https://github.com/collective/collective.fieldedit
Author: Philip Bauer
Author-email: bauer@starzel.de
License: GPL version 2
Project-URL: PyPI, https://pypi.python.org/pypi/collective.fieldedit
Project-URL: Source, https://github.com/collective/collective.fieldedit
Project-URL: Tracker, https://github.com/collective/collective.fieldedit/issues
Keywords: Python Plone
Platform: UNKNOWN
Classifier: Development Status :: 5 - Production/Stable
Classifier: Intended Audience :: Developers
Classifier: Environment :: Web Environment
Classifier: Framework :: Plone
Classifier: Framework :: Plone :: Addon
Classifier: Framework :: Plone :: 5.1
Classifier: Framework :: Plone :: 5.2
Classifier: Framework :: Plone :: 6.0
Classifier: Programming Language :: Python
Classifier: Programming Language :: Python :: 2.7
Classifier: Programming Language :: Python :: 3.6
Classifier: Programming Language :: Python :: 3.7
Classifier: Programming Language :: Python :: 3.8
Classifier: Programming Language :: Python :: 3.9
Classifier: Operating System :: OS Independent
Classifier: License :: OSI Approved :: GNU General Public License v2 (GPLv2)
Requires-Python: >=2.7, !=3.0.*, !=3.1.*, !=3.2.*, !=3.3.*, !=3.4.*, !=3.5.*
Provides-Extra: test
